segmentation_models_pytorch/__init__.py
segmentation_models_pytorch/__version__.py
segmentation_models_pytorch/base/__init__.py
segmentation_models_pytorch/base/heads.py
segmentation_models_pytorch/base/initialization.py
segmentation_models_pytorch/base/model.py
segmentation_models_pytorch/base/modules.py
segmentation_models_pytorch/datasets/__init__.py
segmentation_models_pytorch/datasets/oxford_pet.py
segmentation_models_pytorch/decoders/__init__.py
segmentation_models_pytorch/decoders/deeplabv3/__init__.py
segmentation_models_pytorch/decoders/deeplabv3/decoder.py
segmentation_models_pytorch/decoders/deeplabv3/model.py
segmentation_models_pytorch/decoders/fpn/__init__.py
segmentation_models_pytorch/decoders/fpn/decoder.py
segmentation_models_pytorch/decoders/fpn/model.py
segmentation_models_pytorch/decoders/linknet/__init__.py
segmentation_models_pytorch/decoders/linknet/decoder.py
segmentation_models_pytorch/decoders/linknet/model.py
segmentation_models_pytorch/decoders/manet/__init__.py
segmentation_models_pytorch/decoders/manet/decoder.py
segmentation_models_pytorch/decoders/manet/model.py
segmentation_models_pytorch/decoders/pan/__init__.py
segmentation_models_pytorch/decoders/pan/decoder.py
segmentation_models_pytorch/decoders/pan/model.py
segmentation_models_pytorch/decoders/pspnet/__init__.py
segmentation_models_pytorch/decoders/pspnet/decoder.py
segmentation_models_pytorch/decoders/pspnet/model.py
segmentation_models_pytorch/decoders/unet/__init__.py
segmentation_models_pytorch/decoders/unet/decoder.py
segmentation_models_pytorch/decoders/unet/model.py
segmentation_models_pytorch/decoders/unetplusplus/__init__.py
segmentation_models_pytorch/decoders/unetplusplus/decoder.py
segmentation_models_pytorch/decoders/unetplusplus/model.py
segmentation_models_pytorch/encoders/__init__.py
segmentation_models_pytorch/encoders/_base.py
segmentation_models_pytorch/encoders/_preprocessing.py
segmentation_models_pytorch/encoders/_utils.py
segmentation_models_pytorch_deepflash2-0.3.0.dist-info/LICENSE
segmentation_models_pytorch_deepflash2-0.3.0.dist-info/METADATA
segmentation_models_pytorch_deepflash2-0.3.0.dist-info/WHEEL
segmentation_models_pytorch_deepflash2-0.3.0.dist-info/top_level.txt
segmentation_models_pytorch_deepflash2-0.3.0.dist-info/RECORD
