Metadata-Version: 2.1
Name: segmentation-models-pytorch-deepflash2
Version: 0.3.0
Summary: Image segmentation models with pre-trained backbones. PyTorch. Adapted for deepflash2
Home-page: https://github.com/qubvel/segmentation_models.pytorch
Author: Pavel Yakubovskiy
Author-email: qubvel@gmail.com
License: MIT
Classifier: License :: OSI Approved :: MIT License
Classifier: Programming Language :: Python
Classifier: Programming Language :: Python :: 3
Classifier: Programming Language :: Python :: Implementation :: CPython
Classifier: Programming Language :: Python :: Implementation :: PyPy
Requires-Python: >=3.6.0
License-File: LICENSE
Requires-Dist: torchvision (>=0.5.0)
Requires-Dist: pretrainedmodels (==0.7.4)
Requires-Dist: efficientnet-pytorch (==0.6.3)
Requires-Dist: timm (>=0.5.4)
Requires-Dist: tqdm
Requires-Dist: pillow
Provides-Extra: test
Requires-Dist: pytest ; extra == 'test'
Requires-Dist: mock ; extra == 'test'
Requires-Dist: pre-commit ; extra == 'test'
Requires-Dist: flake8 (==4.0.1) ; extra == 'test'
Requires-Dist: flake8-docstrings (==1.6.0) ; extra == 'test'
